src/__init__.py
src/espresso_machine/__init__.py
src/espresso_machine/check.py
src/espresso_machine/checks.py
src/espresso_machine/compute.py
src/espresso_machine/config.py
src/espresso_machine/generate.py
src/espresso_machine/kpoints.py
src/espresso_machine/ph.py
src/espresso_machine/ph_plot.py
src/espresso_machine/plot_band.py
src/espresso_machine/plot_sigma_energy.py
src/espresso_machine/plots.py
src/espresso_machine/project.py
src/espresso_machine/reads.py
src/espresso_machine/remote.py
src/espresso_machine/run.py
src/espresso_machine/scaffold.py
src/espresso_machine/slurm.py
src/espresso_machine/structure.py
src/espresso_machine/utils.py
src/espresso_machine/writes.py
src/espresso_machine/seekpath/__init__.py
src/espresso_machine/seekpath/getpaths.py
src/espresso_machine/seekpath/util.py
src/espresso_machine/seekpath/brillouinzone/__init__.py
src/espresso_machine/seekpath/brillouinzone/brillouinzone.py
src/espresso_machine/seekpath/hpkot/__init__.py
src/espresso_machine/seekpath/hpkot/spg_db.py
src/espresso_machine/seekpath/hpkot/spg_mapping.py
src/espresso_machine/seekpath/hpkot/tools.py
espresso_machine-0.0.225.dist-info/LICENSE
espresso_machine-0.0.225.dist-info/METADATA
espresso_machine-0.0.225.dist-info/WHEEL
espresso_machine-0.0.225.dist-info/top_level.txt
espresso_machine-0.0.225.dist-info/RECORD
