Metadata-Version: 2.1
Name: espresso-machine
Version: 0.0.225
Summary: Quantum Espresso automation tool
Home-page: https://github.com/susyexstsi/espresso-machine
Author: Susy Exists
Author-email: susy@selectron.me
Keywords: pypi,cicd,python
Classifier: Programming Language :: Python :: 3
Classifier: License :: OSI Approved :: MIT License
Classifier: Operating System :: OS Independent
License-File: LICENSE
Requires-Dist: numpy
Requires-Dist: matplotlib
Requires-Dist: pandas
Requires-Dist: qcelemental
Requires-Dist: ase
Requires-Dist: Flask
Requires-Dist: qe-tools
Requires-Dist: scipy
Requires-Dist: seekpath
Requires-Dist: untangle
Requires-Dist: tools-barebone
Requires-Dist: ipykernel
Requires-Dist: ipython
